odoo/addons/product_contract_variable_quantity/README.rst
odoo/addons/product_contract_variable_quantity/__init__.py
odoo/addons/product_contract_variable_quantity/__manifest__.py
odoo/addons/product_contract_variable_quantity/i18n/fr.po
odoo/addons/product_contract_variable_quantity/i18n/it.po
odoo/addons/product_contract_variable_quantity/i18n/product_contract_variable_quantity.pot
odoo/addons/product_contract_variable_quantity/i18n/pt.po
odoo/addons/product_contract_variable_quantity/i18n/pt_BR.po
odoo/addons/product_contract_variable_quantity/models/__init__.py
odoo/addons/product_contract_variable_quantity/models/contract_line.py
odoo/addons/product_contract_variable_quantity/models/product_template.py
odoo/addons/product_contract_variable_quantity/models/sale_order_line.py
odoo/addons/product_contract_variable_quantity/models/sale_order_line_contract_mixin.py
odoo/addons/product_contract_variable_quantity/readme/CONTRIBUTORS.md
odoo/addons/product_contract_variable_quantity/readme/DESCRIPTION.md
odoo/addons/product_contract_variable_quantity/static/description/icon.png
odoo/addons/product_contract_variable_quantity/static/description/index.html
odoo/addons/product_contract_variable_quantity/static/src/js/contract_configurator_controller.esm.js
odoo/addons/product_contract_variable_quantity/static/src/js/sale_product_field.esm.js
odoo/addons/product_contract_variable_quantity/tests/__init__.py
odoo/addons/product_contract_variable_quantity/tests/test_sale_order.py
odoo/addons/product_contract_variable_quantity/views/product_template.xml
odoo/addons/product_contract_variable_quantity/views/sale_order.xml
odoo/addons/product_contract_variable_quantity/wizards/product_contract_configurator.xml
odoo_addon_product_contract_variable_quantity-18.0.1.0.1.dist-info/METADATA
odoo_addon_product_contract_variable_quantity-18.0.1.0.1.dist-info/WHEEL
odoo_addon_product_contract_variable_quantity-18.0.1.0.1.dist-info/top_level.txt
odoo_addon_product_contract_variable_quantity-18.0.1.0.1.dist-info/RECORD
